ifood_ds_utils/__init__.py
ifood_ds_utils/main.py
ifood_ds_utils-0.3.dist-info/entry_points.txt
ifood_ds_utils-0.3.dist-info/WHEEL
ifood_ds_utils-0.3.dist-info/METADATA
ifood_ds_utils-0.3.dist-info/RECORD
