Metadata-Version: 2.1
Name: ifood-ds-utils
Version: 0.3
Summary: 
Author: Javier Daza
Author-email: javier.olivella@ifood.com
Requires-Python: >=3.8,<4.0
Classifier: Programming Language :: Python :: 3
Classifier: Programming Language :: Python :: 3.10
Classifier: Programming Language :: Python :: 3.8
Classifier: Programming Language :: Python :: 3.9
Requires-Dist: click (>=8.1.3,<9.0.0)
Requires-Dist: colorama (>=0.4.5,<0.5.0)
Requires-Dist: directory-tree (>=0.0.2,<0.0.3)
Requires-Dist: ifood-aws-login (==2.4.8)
